README.md
setup.py
xnlp_time/__init__.py
xnlp_time/filters.py
xnlp_time/pytime.py
xnlp_time/re.txt
xnlp_time.egg-info/PKG-INFO
xnlp_time.egg-info/SOURCES.txt
xnlp_time.egg-info/dependency_links.txt
xnlp_time.egg-info/requires.txt
xnlp_time.egg-info/top_level.txt
xnlp_time.egg-info/zip-safe
xnlp_time/retime/__init__.py
xnlp_time/retime/days.py
xnlp_time/retime/formats.py
xnlp_time/retime/hours.py
xnlp_time/retime/lunarholiday.py
xnlp_time/retime/minutes.py
xnlp_time/retime/months.py
xnlp_time/retime/seconds.py
xnlp_time/retime/solarholiday.py
xnlp_time/retime/solarterm24.py
xnlp_time/retime/specialholiday.py
xnlp_time/retime/weeks.py
xnlp_time/retime/years.py