Metadata-Version: 2.1
Name: xnlp-time
Version: 1.0.0
Summary: 字符串时间解析
Home-page: https://github.com/PyUnit/pyunit-time
Author: xnlp
Author-email: xxx@163.com
License: MIT Licence
Platform: any
Classifier: Programming Language :: Python :: 3
Classifier: License :: OSI Approved :: MIT License
Classifier: Operating System :: OS Independent
